toolshelf/__init__.py
toolshelf/toolshelf.py
toolshelf-0.1.8.dist-info/METADATA
toolshelf-0.1.8.dist-info/WHEEL
toolshelf-0.1.8.dist-info/top_level.txt
toolshelf-0.1.8.dist-info/RECORD
