Metadata-Version: 2.1
Name: toolshelf
Version: 0.1.8
Summary: ICESat-2 data analysis tools
Home-page: UNKNOWN
Author: chancelor roberts
Author-email: ccroberts@ucsd.edu
License: UNKNOWN
Platform: UNKNOWN
Classifier: Development Status :: 3 - Alpha
Classifier: Intended Audience :: Developers
Classifier: License :: OSI Approved :: MIT License
Classifier: Programming Language :: Python :: 3
Classifier: Programming Language :: Python :: 3.6
Classifier: Programming Language :: Python :: 3.7
Classifier: Programming Language :: Python :: 3.8
Classifier: Programming Language :: Python :: 3.9
Classifier: License :: OSI Approved
Requires-Dist: numpy
Requires-Dist: requests
Requires-Dist: h5py
Requires-Dist: earthengine-api
Requires-Dist: folium
